enex2md/__init__.py
enex2md/cli.py
enex2md/convert.py
enex2md-0.4.2.dist-info/LICENSE
enex2md-0.4.2.dist-info/METADATA
enex2md-0.4.2.dist-info/WHEEL
enex2md-0.4.2.dist-info/entry_points.txt
enex2md-0.4.2.dist-info/top_level.txt
enex2md-0.4.2.dist-info/RECORD
