Metadata-Version: 2.1
Name: enex2md
Version: 0.4.2
Summary: Convert enex to Markdown.
Home-page: https://github.com/janikarh/enex2md
Author: Jani Karhunen
Author-email: janikarh@gmail.com
License: MIT
Platform: UNKNOWN
Classifier: Development Status :: 4 - Beta
Classifier: License :: OSI Approved :: MIT License
Classifier: Programming Language :: Python
Classifier: Programming Language :: Python :: 3
Classifier: Programming Language :: Python :: 3.6
Classifier: Programming Language :: Python :: 3.7
Classifier: Programming Language :: Python :: 3.8
Classifier: Topic :: Text Processing
Classifier: Topic :: Utilities
Requires-Python: >=3.6.0
Requires-Dist: Click (>=7.0)
Requires-Dist: lxml (>=4.4.1)
Requires-Dist: python-dateutil (>=2.7.0)
Requires-Dist: html2text (>=2019.9.26)
Requires-Dist: beautifulsoup4 (>=4.8.1)
